rustynum/functions.py
rustynum/num_array_class.py
rustynum/__init__.py
rustynum/_rustynum.cpython-313-x86_64-linux-musl.so
rustynum-0.1.7.dist-info/WHEEL
rustynum-0.1.7.dist-info/METADATA
rustynum-0.1.7.dist-info/RECORD
rustynum-0.1.7.dist-info/top_level.txt
rustynum.libs/libgcc_s-a3a07607.so.1
